calc/__init__.py
calc/module1.py
pizza_slice-1.1.0.dist-info/LICENSE
pizza_slice-1.1.0.dist-info/METADATA
pizza_slice-1.1.0.dist-info/WHEEL
pizza_slice-1.1.0.dist-info/top_level.txt
pizza_slice-1.1.0.dist-info/RECORD
