Metadata-Version: 2.1
Name: pizza-slice
Version: 1.1.0
Summary: A Python package to get sum or subtraction for two values.
Home-page: https://github.com/lkakada/Prime-Number
Author: Kakada Ly
Author-email: ly103399@gmail.com
License: MIT
Platform: UNKNOWN
Classifier: License :: OSI Approved :: MIT License
Classifier: Programming Language :: Python :: 3
Classifier: Programming Language :: Python :: 3.7
Requires-Dist: Flask (==1.0.2)
